amoapi/__init__.py
amoapi/amoapi_basic.py
amoapi/exceptions.py
amoapi/filters.py
amoapi/interaction.py
amoapi/tokens.py
amoapi-0.0.5.dist-info/METADATA
amoapi-0.0.5.dist-info/WHEEL
amoapi-0.0.5.dist-info/top_level.txt
amoapi-0.0.5.dist-info/RECORD
