Metadata-Version: 2.1
Name: amoapi
Version: 0.0.5
Summary: Simple python wrapper for some parts of the amocrm API (https://www.amocrm.ru/developers/content/crm_platform/api-reference)
Home-page: https://github.com/megrano/amoapi/
Author: Mihail Granovskij
Author-email: mihail.granovskij@gmail.com
License: UNKNOWN
Project-URL: Bug Tracker, https://github.com/megrano/amoapi/issues
Platform: UNKNOWN
Classifier: Programming Language :: Python :: 3
Classifier: License :: OSI Approved :: MIT License
Classifier: Operating System :: OS Independent
Requires-Python: >=3.6
Requires-Dist: requests
